cdataml/__init__.py
cdataml/cdametadata.py
cdataml/datainput.py
cdataml/lesion_score_key.tif
cdataml/test.txt
cdataml-0.5.15.data/scripts/cdataml-run
cdataml-0.5.15.dist-info/LICENSE
cdataml-0.5.15.dist-info/METADATA
cdataml-0.5.15.dist-info/WHEEL
cdataml-0.5.15.dist-info/top_level.txt
cdataml-0.5.15.dist-info/RECORD
