Metadata-Version: 2.1
Name: cdataml
Version: 0.5.15
Summary: Cell Death Area Data Collection for Machine Learning
Home-page: https://github.com/joshuandwilliams/cdataml
Author: Joshua Williams
Author-email: <jowillia@nbi.ac.uk>
License: LICENSE.txt
License-File: LICENSE
Requires-Dist: opencv-python
Requires-Dist: pandas
Requires-Dist: natsort
Requires-Dist: importlib-resources
